{
    "id": 124539978,
    "name": "EdvardSlaughtehouse",
    "author": "AcrylicLV ",
    "creators": ["AcrylicLV"],
    "verifier": "AcrylicLV",
    "verification": "https://www.youtube.com/watch?v=lD1tVRQHsdk",
    "percentToQualify": "100",
    "password": "Copyable",
    "records": [
        {
            "user": "kurtiscoool",
            "link": "https://www.youtube.com/watch?v=Al-Le9fdEtI",
            "percent": 100,
            "hz": 240
        },
        {
            "user": "Morska",
            "link": "https://www.youtube.com/watch?v=oudMs9g-WAY",
            "percent": 100,
            "hz": 144
        },
        {
            "user": "Luky1515",
            "link": "https://youtu.be/vnugybV4TQc",
            "percent": 100,
            "hz": 144
        },
        {
            "user": "payloooad",
            "link": "https://youtu.be/Stv6rbWIUh4",
            "percent": 100,
            "hz": "N/A"
        },
        {
            "user": "Termy",
            "link": "https://www.youtube.com/watch?v=3-Dw3XS6Uo8",
            "percent": 100,
            "hz": 240
        },
        {
            "user": "jeremyballerton",
            "link": "https://www.youtube.com/watch?v=qGcngOMQb08",
            "percent": 100,
            "hz": 240
        },
        {
            "user": "MatesM",
            "link": "https://www.youtube.com/watch?v=0kNpCMB1LBo",
            "percent": 100,
            "hz": 460
        },
        {
            "user": "4Genesis",
            "link": "https://youtu.be/bVRjJOGiAfg",
            "percent": 100,
            "hz": 60
        },
        {
            "user": "ak4c",
            "link": "https://youtu.be/4I0Va2m1xRg",
            "percent": 100,
            "hz": 240
        },
        {
            "user": "MayXaX",
            "link": "https://medal.tv/games/geometry-dash/clips/mQfeC6cbkQtQY7Wkp?invite=cr-MSxLTXAsMzg2Mzc3NzM0&v=55",
            "percent": 100,
            "hz": 360
        },
         {
            "user": "Loxuty123",
            "link": "https://medal.tv/games/geometry-dash/clips/mQf2HuGcQZvNGcN1C?invite=cr-MSxoZG0sNTg0NDA0OTI1",
            "percent": 100,
            "hz": 360
        },
         {
            "user": "leo",
            "link": "https://medal.tv/games/geometry-dash/clips/mQanNoBW21MxN__7I?invite=cr-MSw3VzksNDA1NTgyMjkw&v=134",
            "percent": 100,
            "hz": 700
        },
        {
            "user": "eistee_king1234",
            "link": "https://youtube.com/shorts/3F7u74FKCBI?si=UZkwtLuCmZAvCI5v",
            "percent": 100,
            "hz": 60
        }
    ]
}
